collectiontools_vrb/__init__.py
collectiontools_vrb/__version__.py
collectiontools_vrb/collectiontranslator.py
collectiontools_vrb/py.typed
collectiontools_vrb-0.9.2.dist-info/METADATA
collectiontools_vrb-0.9.2.dist-info/WHEEL
collectiontools_vrb-0.9.2.dist-info/licenses/LICENSE
collectiontools_vrb-0.9.2.dist-info/RECORD
