Metadata-Version: 2.4
Name: collectiontools_vrb
Version: 0.9.2
Summary: Various tools to handle collection I/O and transformations
Project-URL: Homepage, https://github.com/v-r-b/collectiontools_vrb
Project-URL: Issues, https://github.com/v-r-b/collectiontools_vrb/issues
Author-email: volker <volker@vrbdev.eu>
Maintainer-email: volker <volker@vrbdev.eu>
License-Expression: GPL-3.0-or-later
License-File: LICENSE
Classifier: Development Status :: 4 - Beta
Classifier: Intended Audience :: Developers
Classifier: License :: OSI Approved :: GNU General Public License v3 (GPLv3)
Classifier: Operating System :: OS Independent
Classifier: Programming Language :: Python :: 3
Classifier: Topic :: Software Development :: Libraries :: Python Modules
Requires-Python: >=3.9
Requires-Dist: aiohttp
